mycalc/calculator.py
hyj230411-1.0.1.dist-info/METADATA
hyj230411-1.0.1.dist-info/WHEEL
hyj230411-1.0.1.dist-info/top_level.txt
hyj230411-1.0.1.dist-info/RECORD
