Metadata-Version: 2.1
Name: hyj230411
Version: 1.0.1
Summary: nice calc
Author: HanYuJun
License: UNKNOWN
Platform: UNKNOWN
Classifier: Programming Language :: Python :: 3
